{
  "trained_at": "2026-04-12T21:40:30.380331",
  "version": "v2_regime_aware",
  "algorithm": "PPO",
  "feature_cols": [
    "4h_candle_bull",
    "4h_return_1",
    "4h_stoch_rsi",
    "1d_candle_bull",
    "4h_ema_9_dist",
    "4h_bb_pos",
    "1d_return_1",
    "4h_return_3",
    "4h_obv_norm",
    "4h_rsi_14",
    "4h_upper_wick",
    "4h_lower_wick",
    "4h_ema_21_dist",
    "1d_ema_9_dist",
    "1d_stoch_rsi",
    "1d_bb_pos",
    "1d_return_3",
    "4h_return_6",
    "1d_obv_norm",
    "1d_rsi_14",
    "1h_ema_9_dist",
    "4h_ema_50_dist",
    "1d_ema_21_dist",
    "1h_bb_pos",
    "4h_rsi_overbought",
    "1h_return_3",
    "1h_stoch_rsi",
    "1h_rsi_14",
    "4h_return_12",
    "1h_ema_21_dist",
    "1d_return_6",
    "15m_minus_di",
    "1h_return_6",
    "15m_bb_pos",
    "1h_obv_norm",
    "1h_return_1",
    "15m_rsi_14",
    "1h_candle_bull",
    "15m_ema_21_dist",
    "15m_plus_di",
    "1d_ema_50_dist",
    "1h_minus_di",
    "15m_ema_9_dist",
    "1h_plus_di",
    "15m_ema_50_dist",
    "15m_ema_9_above_21",
    "4h_rsi_oversold",
    "1h_ema_50_dist",
    "ca_div_z_16",
    "1h_return_12",
    "4h_plus_di",
    "15m_return_12",
    "15m_obv_norm"
  ],
  "regime_cols": [
    "1h_adx",
    "1h_chop",
    "1h_vol_regime",
    "1h_bb_squeeze",
    "1h_trend_consistency",
    "1h_regime_trend"
  ],
  "n_features": 53,
  "n_regime": 6,
  "n_obs": 63,
  "n_train": 26721,
  "n_test": 6681,
  "total_timesteps": 800000,
  "hyperparams": {
    "learning_rate": 0.0002,
    "gamma": 0.995,
    "ent_coef": 0.015,
    "n_steps": 2048,
    "batch_size": 256,
    "net_arch": "pi=[128,128], vf=[128,128]"
  },
  "test_return": 10.9685,
  "test_pnl": 12727.33,
  "test_trades": 3923,
  "test_win_rate": 0.6602,
  "test_sharpe": 27.26,
  "test_trend_trades": 1049,
  "test_side_trades": 2874,
  "test_trend_pnl": 5241.14,
  "test_side_pnl": 7486.19,
  "training_progress": [
    {
      "step": 10000,
      "reward": -3.5605,
      "capital": 835.58,
      "pnl": -98.01,
      "trades": 2807,
      "win_rate": 0.451,
      "fees": 132.82,
      "sharpe": -7.74,
      "trend_trades": 746,
      "side_trades": 2061,
      "trend_pnl": -43.65,
      "side_pnl": -54.36
    },
    {
      "step": 20000,
      "reward": -3.7337,
      "capital": 641.16,
      "pnl": -241.73,
      "trades": 3970,
      "win_rate": 0.454,
      "fees": 234.21,
      "sharpe": -13.28,
      "trend_trades": 1073,
      "side_trades": 2897,
      "trend_pnl": -126.47,
      "side_pnl": -115.26
    },
    {
      "step": 30000,
      "reward": -4.0182,
      "capital": 806.72,
      "pnl": -41.02,
      "trades": 3994,
      "win_rate": 0.503,
      "fees": 304.53,
      "sharpe": -5.55,
      "trend_trades": 1015,
      "side_trades": 2979,
      "trend_pnl": -88.88,
      "side_pnl": 47.87
    },
    {
      "step": 40000,
      "reward": -3.3951,
      "capital": 1210.44,
      "pnl": 403.99,
      "trades": 4112,
      "win_rate": 0.528,
      "fees": 387.03,
      "sharpe": 4.97,
      "trend_trades": 1005,
      "side_trades": 3107,
      "trend_pnl": 98.5,
      "side_pnl": 305.48
    },
    {
      "step": 50000,
      "reward": -4.0942,
      "capital": 1065.75,
      "pnl": 240.6,
      "trades": 3736,
      "win_rate": 0.509,
      "fees": 349.56,
      "sharpe": 1.62,
      "trend_trades": 969,
      "side_trades": 2767,
      "trend_pnl": 64.64,
      "side_pnl": 175.96
    },
    {
      "step": 60000,
      "reward": -4.352,
      "capital": 1008.93,
      "pnl": 250.53,
      "trades": 4272,
      "win_rate": 0.49,
      "fees": 483.08,
      "sharpe": 0.21,
      "trend_trades": 1116,
      "side_trades": 3156,
      "trend_pnl": 62.41,
      "side_pnl": 188.12
    },
    {
      "step": 70000,
      "reward": -3.9668,
      "capital": 1135.67,
      "pnl": 404.49,
      "trades": 4450,
      "win_rate": 0.493,
      "fees": 537.51,
      "sharpe": 2.09,
      "trend_trades": 1216,
      "side_trades": 3234,
      "trend_pnl": 155.21,
      "side_pnl": 249.28
    },
    {
      "step": 80000,
      "reward": -3.9275,
      "capital": 1437.47,
      "pnl": 772.15,
      "trades": 4565,
      "win_rate": 0.517,
      "fees": 669.18,
      "sharpe": 5.52,
      "trend_trades": 1169,
      "side_trades": 3396,
      "trend_pnl": 235.47,
      "side_pnl": 536.67
    },
    {
      "step": 90000,
      "reward": -3.8999,
      "capital": 1614.88,
      "pnl": 996.06,
      "trades": 4653,
      "win_rate": 0.519,
      "fees": 762.2,
      "sharpe": 7.09,
      "trend_trades": 1228,
      "side_trades": 3425,
      "trend_pnl": 269.66,
      "side_pnl": 726.4
    },
    {
      "step": 100000,
      "reward": -3.4179,
      "capital": 1906.88,
      "pnl": 1338.83,
      "trades": 4826,
      "win_rate": 0.533,
      "fees": 863.78,
      "sharpe": 9.39,
      "trend_trades": 1266,
      "side_trades": 3560,
      "trend_pnl": 353.27,
      "side_pnl": 985.57
    },
    {
      "step": 110000,
      "reward": -3.8273,
      "capital": 1974.37,
      "pnl": 1443.25,
      "trades": 4740,
      "win_rate": 0.541,
      "fees": 937.64,
      "sharpe": 9.16,
      "trend_trades": 1239,
      "side_trades": 3501,
      "trend_pnl": 331.84,
      "side_pnl": 1111.41
    },
    {
      "step": 120000,
      "reward": -3.0494,
      "capital": 2619.83,
      "pnl": 2202.93,
      "trades": 4831,
      "win_rate": 0.552,
      "fees": 1166.11,
      "sharpe": 12.61,
      "trend_trades": 1295,
      "side_trades": 3536,
      "trend_pnl": 573.24,
      "side_pnl": 1629.69
    },
    {
      "step": 130000,
      "reward": -0.9373,
      "capital": 4344.96,
      "pnl": 4163.56,
      "trades": 4848,
      "win_rate": 0.588,
      "fees": 1637.22,
      "sharpe": 18.97,
      "trend_trades": 1289,
      "side_trades": 3559,
      "trend_pnl": 1403.84,
      "side_pnl": 2759.73
    },
    {
      "step": 140000,
      "reward": -0.2272,
      "capital": 5139.23,
      "pnl": 5080.55,
      "trades": 4824,
      "win_rate": 0.601,
      "fees": 1882.52,
      "sharpe": 20.52,
      "trend_trades": 1259,
      "side_trades": 3565,
      "trend_pnl": 1728.52,
      "side_pnl": 3352.03
    },
    {
      "step": 150000,
      "reward": 0.7751,
      "capital": 6238.17,
      "pnl": 6321.38,
      "trades": 4709,
      "win_rate": 0.61,
      "fees": 2166.3,
      "sharpe": 22.38,
      "trend_trades": 1247,
      "side_trades": 3462,
      "trend_pnl": 2274.87,
      "side_pnl": 4046.51
    },
    {
      "step": 160000,
      "reward": 2.0517,
      "capital": 7384.62,
      "pnl": 7610.02,
      "trades": 4667,
      "win_rate": 0.613,
      "fees": 2450.66,
      "sharpe": 23.92,
      "trend_trades": 1259,
      "side_trades": 3408,
      "trend_pnl": 2873.18,
      "side_pnl": 4736.84
    },
    {
      "step": 170000,
      "reward": 3.2252,
      "capital": 8448.35,
      "pnl": 8816.24,
      "trades": 4620,
      "win_rate": 0.614,
      "fees": 2735.79,
      "sharpe": 25.33,
      "trend_trades": 1265,
      "side_trades": 3355,
      "trend_pnl": 3434.96,
      "side_pnl": 5381.28
    },
    {
      "step": 180000,
      "reward": 4.0066,
      "capital": 9164.92,
      "pnl": 9606.64,
      "trades": 4534,
      "win_rate": 0.62,
      "fees": 2883.35,
      "sharpe": 26.18,
      "trend_trades": 1267,
      "side_trades": 3267,
      "trend_pnl": 3764.46,
      "side_pnl": 5842.18
    },
    {
      "step": 190000,
      "reward": 4.6624,
      "capital": 9862.61,
      "pnl": 10396.27,
      "trades": 4527,
      "win_rate": 0.631,
      "fees": 3067.21,
      "sharpe": 26.79,
      "trend_trades": 1240,
      "side_trades": 3287,
      "trend_pnl": 4162.92,
      "side_pnl": 6233.35
    },
    {
      "step": 200000,
      "reward": 5.7176,
      "capital": 10805.03,
      "pnl": 11425.93,
      "trades": 4444,
      "win_rate": 0.64,
      "fees": 3241.81,
      "sharpe": 27.53,
      "trend_trades": 1216,
      "side_trades": 3228,
      "trend_pnl": 4599.86,
      "side_pnl": 6826.07
    },
    {
      "step": 210000,
      "reward": 6.006,
      "capital": 11116.1,
      "pnl": 11755.97,
      "trades": 4406,
      "win_rate": 0.645,
      "fees": 3279.67,
      "sharpe": 27.78,
      "trend_trades": 1212,
      "side_trades": 3194,
      "trend_pnl": 4708.71,
      "side_pnl": 7047.26
    },
    {
      "step": 220000,
      "reward": 6.2325,
      "capital": 11405.04,
      "pnl": 12064.15,
      "trades": 4330,
      "win_rate": 0.632,
      "fees": 3317.72,
      "sharpe": 27.67,
      "trend_trades": 1202,
      "side_trades": 3128,
      "trend_pnl": 5097.41,
      "side_pnl": 6966.74
    },
    {
      "step": 230000,
      "reward": 6.3902,
      "capital": 11618.89,
      "pnl": 12293.38,
      "trades": 4278,
      "win_rate": 0.641,
      "fees": 3348.22,
      "sharpe": 27.92,
      "trend_trades": 1192,
      "side_trades": 3086,
      "trend_pnl": 5035.38,
      "side_pnl": 7258.0
    },
    {
      "step": 240000,
      "reward": 6.0947,
      "capital": 11461.86,
      "pnl": 12141.73,
      "trades": 4267,
      "win_rate": 0.638,
      "fees": 3358.93,
      "sharpe": 27.74,
      "trend_trades": 1193,
      "side_trades": 3074,
      "trend_pnl": 4962.9,
      "side_pnl": 7178.84
    },
    {
      "step": 250000,
      "reward": 5.6837,
      "capital": 11176.35,
      "pnl": 11794.01,
      "trades": 4166,
      "win_rate": 0.641,
      "fees": 3234.59,
      "sharpe": 27.3,
      "trend_trades": 1154,
      "side_trades": 3012,
      "trend_pnl": 4789.63,
      "side_pnl": 7004.38
    },
    {
      "step": 260000,
      "reward": 6.1889,
      "capital": 11628.17,
      "pnl": 12308.04,
      "trades": 4171,
      "win_rate": 0.642,
      "fees": 3359.01,
      "sharpe": 27.54,
      "trend_trades": 1154,
      "side_trades": 3017,
      "trend_pnl": 5037.28,
      "side_pnl": 7270.75
    },
    {
      "step": 270000,
      "reward": 5.6323,
      "capital": 11202.1,
      "pnl": 11830.46,
      "trades": 4186,
      "win_rate": 0.64,
      "fees": 3256.13,
      "sharpe": 27.16,
      "trend_trades": 1142,
      "side_trades": 3044,
      "trend_pnl": 4808.81,
      "side_pnl": 7021.65
    },
    {
      "step": 280000,
      "reward": 5.6066,
      "capital": 11193.45,
      "pnl": 11851.63,
      "trades": 4216,
      "win_rate": 0.64,
      "fees": 3315.8,
      "sharpe": 27.25,
      "trend_trades": 1165,
      "side_trades": 3051,
      "trend_pnl": 4795.35,
      "side_pnl": 7056.27
    },
    {
      "step": 290000,
      "reward": 6.0278,
      "capital": 11571.23,
      "pnl": 12269.05,
      "trades": 4190,
      "win_rate": 0.642,
      "fees": 3395.05,
      "sharpe": 27.53,
      "trend_trades": 1156,
      "side_trades": 3034,
      "trend_pnl": 5003.64,
      "side_pnl": 7265.41
    },
    {
      "step": 300000,
      "reward": 6.2896,
      "capital": 11798.73,
      "pnl": 12549.2,
      "trades": 4171,
      "win_rate": 0.645,
      "fees": 3500.27,
      "sharpe": 27.46,
      "trend_trades": 1146,
      "side_trades": 3025,
      "trend_pnl": 5208.66,
      "side_pnl": 7340.54
    },
    {
      "step": 310000,
      "reward": 6.9099,
      "capital": 12317.86,
      "pnl": 13138.71,
      "trades": 4163,
      "win_rate": 0.652,
      "fees": 3641.0,
      "sharpe": 27.89,
      "trend_trades": 1142,
      "side_trades": 3021,
      "trend_pnl": 5403.85,
      "side_pnl": 7734.87
    },
    {
      "step": 320000,
      "reward": 7.1737,
      "capital": 12575.08,
      "pnl": 13421.09,
      "trades": 4175,
      "win_rate": 0.654,
      "fees": 3691.21,
      "sharpe": 28.07,
      "trend_trades": 1150,
      "side_trades": 3025,
      "trend_pnl": 5597.76,
      "side_pnl": 7823.32
    },
    {
      "step": 330000,
      "reward": 7.2194,
      "capital": 12654.71,
      "pnl": 13493.73,
      "trades": 4135,
      "win_rate": 0.648,
      "fees": 3677.65,
      "sharpe": 28.24,
      "trend_trades": 1135,
      "side_trades": 3000,
      "trend_pnl": 5553.27,
      "side_pnl": 7940.46
    },
    {
      "step": 340000,
      "reward": 7.04,
      "capital": 12505.95,
      "pnl": 13335.07,
      "trades": 4148,
      "win_rate": 0.647,
      "fees": 3657.76,
      "sharpe": 28.17,
      "trend_trades": 1142,
      "side_trades": 3006,
      "trend_pnl": 5440.46,
      "side_pnl": 7894.61
    },
    {
      "step": 350000,
      "reward": 6.7908,
      "capital": 12182.64,
      "pnl": 12991.36,
      "trades": 4194,
      "win_rate": 0.654,
      "fees": 3616.99,
      "sharpe": 28.02,
      "trend_trades": 1167,
      "side_trades": 3027,
      "trend_pnl": 5203.37,
      "side_pnl": 7788.0
    },
    {
      "step": 360000,
      "reward": 6.7546,
      "capital": 12213.73,
      "pnl": 13004.36,
      "trades": 4151,
      "win_rate": 0.656,
      "fees": 3580.77,
      "sharpe": 28.21,
      "trend_trades": 1147,
      "side_trades": 3004,
      "trend_pnl": 5203.86,
      "side_pnl": 7800.5
    },
    {
      "step": 370000,
      "reward": 6.5043,
      "capital": 12006.15,
      "pnl": 12769.04,
      "trades": 4171,
      "win_rate": 0.655,
      "fees": 3525.32,
      "sharpe": 28.08,
      "trend_trades": 1151,
      "side_trades": 3020,
      "trend_pnl": 5071.59,
      "side_pnl": 7697.45
    },
    {
      "step": 380000,
      "reward": 5.9929,
      "capital": 11564.38,
      "pnl": 12263.98,
      "trades": 4145,
      "win_rate": 0.648,
      "fees": 3398.93,
      "sharpe": 27.48,
      "trend_trades": 1147,
      "side_trades": 2998,
      "trend_pnl": 4877.53,
      "side_pnl": 7386.45
    },
    {
      "step": 390000,
      "reward": 6.1969,
      "capital": 11789.56,
      "pnl": 12513.53,
      "trades": 4148,
      "win_rate": 0.649,
      "fees": 3447.52,
      "sharpe": 27.56,
      "trend_trades": 1146,
      "side_trades": 3002,
      "trend_pnl": 5082.5,
      "side_pnl": 7431.04
    },
    {
      "step": 400000,
      "reward": 6.6216,
      "capital": 12160.33,
      "pnl": 12945.66,
      "trades": 4146,
      "win_rate": 0.647,
      "fees": 3570.56,
      "sharpe": 27.89,
      "trend_trades": 1148,
      "side_trades": 2998,
      "trend_pnl": 5276.43,
      "side_pnl": 7669.23
    },
    {
      "step": 410000,
      "reward": 6.3476,
      "capital": 11944.27,
      "pnl": 12723.01,
      "trades": 4123,
      "win_rate": 0.649,
      "fees": 3557.49,
      "sharpe": 27.57,
      "trend_trades": 1136,
      "side_trades": 2987,
      "trend_pnl": 5268.63,
      "side_pnl": 7454.39
    },
    {
      "step": 420000,
      "reward": 6.2881,
      "capital": 11856.59,
      "pnl": 12612.81,
      "trades": 4131,
      "win_rate": 0.654,
      "fees": 3512.24,
      "sharpe": 27.66,
      "trend_trades": 1137,
      "side_trades": 2994,
      "trend_pnl": 5239.34,
      "side_pnl": 7373.47
    },
    {
      "step": 430000,
      "reward": 6.0424,
      "capital": 11594.17,
      "pnl": 12347.13,
      "trades": 4180,
      "win_rate": 0.654,
      "fees": 3505.93,
      "sharpe": 27.49,
      "trend_trades": 1148,
      "side_trades": 3032,
      "trend_pnl": 5059.98,
      "side_pnl": 7287.15
    },
    {
      "step": 440000,
      "reward": 6.7503,
      "capital": 12344.7,
      "pnl": 13168.36,
      "trades": 4102,
      "win_rate": 0.654,
      "fees": 3647.15,
      "sharpe": 27.75,
      "trend_trades": 1122,
      "side_trades": 2980,
      "trend_pnl": 5632.68,
      "side_pnl": 7535.68
    },
    {
      "step": 450000,
      "reward": 6.6893,
      "capital": 12325.99,
      "pnl": 13144.94,
      "trades": 4114,
      "win_rate": 0.656,
      "fees": 3637.7,
      "sharpe": 27.88,
      "trend_trades": 1117,
      "side_trades": 2997,
      "trend_pnl": 5524.52,
      "side_pnl": 7620.42
    },
    {
      "step": 460000,
      "reward": 6.5616,
      "capital": 12304.26,
      "pnl": 13121.81,
      "trades": 4055,
      "win_rate": 0.655,
      "fees": 3634.17,
      "sharpe": 27.65,
      "trend_trades": 1092,
      "side_trades": 2963,
      "trend_pnl": 5602.94,
      "side_pnl": 7518.87
    },
    {
      "step": 470000,
      "reward": 6.5967,
      "capital": 12369.65,
      "pnl": 13169.97,
      "trades": 4027,
      "win_rate": 0.653,
      "fees": 3599.81,
      "sharpe": 27.78,
      "trend_trades": 1096,
      "side_trades": 2931,
      "trend_pnl": 5487.38,
      "side_pnl": 7682.59
    },
    {
      "step": 480000,
      "reward": 6.3893,
      "capital": 12148.17,
      "pnl": 12953.53,
      "trades": 4065,
      "win_rate": 0.655,
      "fees": 3609.87,
      "sharpe": 27.72,
      "trend_trades": 1098,
      "side_trades": 2967,
      "trend_pnl": 5335.48,
      "side_pnl": 7618.05
    },
    {
      "step": 490000,
      "reward": 6.9085,
      "capital": 12539.92,
      "pnl": 13377.74,
      "trades": 4057,
      "win_rate": 0.653,
      "fees": 3674.82,
      "sharpe": 27.93,
      "trend_trades": 1083,
      "side_trades": 2974,
      "trend_pnl": 5651.71,
      "side_pnl": 7726.03
    },
    {
      "step": 500000,
      "reward": 7.324,
      "capital": 12853.55,
      "pnl": 13719.42,
      "trades": 4033,
      "win_rate": 0.655,
      "fees": 3730.69,
      "sharpe": 28.22,
      "trend_trades": 1081,
      "side_trades": 2952,
      "trend_pnl": 5805.13,
      "side_pnl": 7914.29
    },
    {
      "step": 510000,
      "reward": 7.0802,
      "capital": 12788.34,
      "pnl": 13664.81,
      "trades": 4026,
      "win_rate": 0.655,
      "fees": 3752.06,
      "sharpe": 27.93,
      "trend_trades": 1069,
      "side_trades": 2957,
      "trend_pnl": 5864.45,
      "side_pnl": 7800.36
    },
    {
      "step": 520000,
      "reward": 7.0908,
      "capital": 12835.68,
      "pnl": 13709.76,
      "trades": 4032,
      "win_rate": 0.656,
      "fees": 3746.86,
      "sharpe": 27.99,
      "trend_trades": 1069,
      "side_trades": 2963,
      "trend_pnl": 5866.44,
      "side_pnl": 7843.32
    },
    {
      "step": 530000,
      "reward": 7.0089,
      "capital": 12792.3,
      "pnl": 13648.73,
      "trades": 3977,
      "win_rate": 0.656,
      "fees": 3711.53,
      "sharpe": 27.98,
      "trend_trades": 1057,
      "side_trades": 2920,
      "trend_pnl": 5856.82,
      "side_pnl": 7791.91
    },
    {
      "step": 540000,
      "reward": 7.1033,
      "capital": 12894.44,
      "pnl": 13728.64,
      "trades": 3935,
      "win_rate": 0.654,
      "fees": 3667.26,
      "sharpe": 27.88,
      "trend_trades": 1033,
      "side_trades": 2902,
      "trend_pnl": 5811.45,
      "side_pnl": 7917.19
    },
    {
      "step": 550000,
      "reward": 7.0963,
      "capital": 12856.11,
      "pnl": 13699.96,
      "trades": 3950,
      "win_rate": 0.658,
      "fees": 3686.44,
      "sharpe": 27.97,
      "trend_trades": 1035,
      "side_trades": 2915,
      "trend_pnl": 5683.77,
      "side_pnl": 8016.19
    },
    {
      "step": 560000,
      "reward": 6.8382,
      "capital": 12597.7,
      "pnl": 13419.43,
      "trades": 3989,
      "win_rate": 0.653,
      "fees": 3642.29,
      "sharpe": 27.79,
      "trend_trades": 1070,
      "side_trades": 2919,
      "trend_pnl": 5517.81,
      "side_pnl": 7901.62
    },
    {
      "step": 570000,
      "reward": 6.7643,
      "capital": 12362.9,
      "pnl": 13179.17,
      "trades": 4097,
      "win_rate": 0.652,
      "fees": 3631.65,
      "sharpe": 27.85,
      "trend_trades": 1087,
      "side_trades": 3010,
      "trend_pnl": 5325.83,
      "side_pnl": 7853.34
    },
    {
      "step": 580000,
      "reward": 6.983,
      "capital": 12548.27,
      "pnl": 13367.07,
      "trades": 4053,
      "win_rate": 0.657,
      "fees": 3636.91,
      "sharpe": 27.97,
      "trend_trades": 1072,
      "side_trades": 2981,
      "trend_pnl": 5483.4,
      "side_pnl": 7883.67
    },
    {
      "step": 590000,
      "reward": 7.0359,
      "capital": 12727.89,
      "pnl": 13579.49,
      "trades": 4034,
      "win_rate": 0.658,
      "fees": 3702.03,
      "sharpe": 28.12,
      "trend_trades": 1071,
      "side_trades": 2963,
      "trend_pnl": 5651.83,
      "side_pnl": 7927.66
    },
    {
      "step": 600000,
      "reward": 7.1004,
      "capital": 12802.71,
      "pnl": 13667.42,
      "trades": 4024,
      "win_rate": 0.659,
      "fees": 3728.55,
      "sharpe": 28.05,
      "trend_trades": 1081,
      "side_trades": 2943,
      "trend_pnl": 5634.44,
      "side_pnl": 8032.97
    },
    {
      "step": 610000,
      "reward": 7.2069,
      "capital": 12886.05,
      "pnl": 13747.03,
      "trades": 4013,
      "win_rate": 0.661,
      "fees": 3721.19,
      "sharpe": 28.17,
      "trend_trades": 1085,
      "side_trades": 2928,
      "trend_pnl": 5722.54,
      "side_pnl": 8024.49
    },
    {
      "step": 620000,
      "reward": 7.3236,
      "capital": 13022.6,
      "pnl": 13903.59,
      "trades": 3998,
      "win_rate": 0.662,
      "fees": 3761.98,
      "sharpe": 28.19,
      "trend_trades": 1086,
      "side_trades": 2912,
      "trend_pnl": 5821.66,
      "side_pnl": 8081.93
    },
    {
      "step": 630000,
      "reward": 7.3345,
      "capital": 13018.42,
      "pnl": 13903.55,
      "trades": 3990,
      "win_rate": 0.664,
      "fees": 3769.94,
      "sharpe": 28.17,
      "trend_trades": 1086,
      "side_trades": 2904,
      "trend_pnl": 5845.04,
      "side_pnl": 8058.51
    },
    {
      "step": 640000,
      "reward": 7.2668,
      "capital": 13009.38,
      "pnl": 13878.11,
      "trades": 3965,
      "win_rate": 0.661,
      "fees": 3737.09,
      "sharpe": 28.1,
      "trend_trades": 1086,
      "side_trades": 2879,
      "trend_pnl": 5800.61,
      "side_pnl": 8077.49
    },
    {
      "step": 650000,
      "reward": 7.2395,
      "capital": 12978.87,
      "pnl": 13848.94,
      "trades": 3978,
      "win_rate": 0.662,
      "fees": 3739.22,
      "sharpe": 28.28,
      "trend_trades": 1082,
      "side_trades": 2896,
      "trend_pnl": 5682.85,
      "side_pnl": 8166.09
    },
    {
      "step": 660000,
      "reward": 7.1729,
      "capital": 12939.26,
      "pnl": 13812.18,
      "trades": 3978,
      "win_rate": 0.663,
      "fees": 3745.28,
      "sharpe": 28.15,
      "trend_trades": 1077,
      "side_trades": 2901,
      "trend_pnl": 5712.39,
      "side_pnl": 8099.79
    },
    {
      "step": 670000,
      "reward": 6.4874,
      "capital": 12366.18,
      "pnl": 13202.37,
      "trades": 4016,
      "win_rate": 0.658,
      "fees": 3671.03,
      "sharpe": 27.57,
      "trend_trades": 1089,
      "side_trades": 2927,
      "trend_pnl": 5389.69,
      "side_pnl": 7812.68
    },
    {
      "step": 680000,
      "reward": 6.3515,
      "capital": 12199.41,
      "pnl": 13016.72,
      "trades": 3987,
      "win_rate": 0.661,
      "fees": 3633.19,
      "sharpe": 27.48,
      "trend_trades": 1089,
      "side_trades": 2898,
      "trend_pnl": 5285.69,
      "side_pnl": 7731.03
    },
    {
      "step": 690000,
      "reward": 6.3502,
      "capital": 12203.26,
      "pnl": 13028.11,
      "trades": 3989,
      "win_rate": 0.66,
      "fees": 3648.24,
      "sharpe": 27.46,
      "trend_trades": 1093,
      "side_trades": 2896,
      "trend_pnl": 5297.7,
      "side_pnl": 7730.41
    },
    {
      "step": 700000,
      "reward": 6.0073,
      "capital": 12025.6,
      "pnl": 12818.41,
      "trades": 3963,
      "win_rate": 0.663,
      "fees": 3584.17,
      "sharpe": 27.19,
      "trend_trades": 1072,
      "side_trades": 2891,
      "trend_pnl": 5172.19,
      "side_pnl": 7646.21
    },
    {
      "step": 710000,
      "reward": 5.6374,
      "capital": 11682.41,
      "pnl": 12461.49,
      "trades": 3991,
      "win_rate": 0.658,
      "fees": 3557.15,
      "sharpe": 26.86,
      "trend_trades": 1062,
      "side_trades": 2929,
      "trend_pnl": 5002.6,
      "side_pnl": 7458.89
    },
    {
      "step": 720000,
      "reward": 5.7518,
      "capital": 11748.36,
      "pnl": 12530.08,
      "trades": 3993,
      "win_rate": 0.659,
      "fees": 3562.14,
      "sharpe": 26.93,
      "trend_trades": 1078,
      "side_trades": 2915,
      "trend_pnl": 5106.51,
      "side_pnl": 7423.57
    },
    {
      "step": 730000,
      "reward": 5.7296,
      "capital": 11739.77,
      "pnl": 12521.56,
      "trades": 4003,
      "win_rate": 0.656,
      "fees": 3562.19,
      "sharpe": 26.94,
      "trend_trades": 1071,
      "side_trades": 2932,
      "trend_pnl": 5098.29,
      "side_pnl": 7423.28
    },
    {
      "step": 740000,
      "reward": 5.8938,
      "capital": 11890.36,
      "pnl": 12673.59,
      "trades": 3997,
      "win_rate": 0.658,
      "fees": 3565.04,
      "sharpe": 27.13,
      "trend_trades": 1077,
      "side_trades": 2920,
      "trend_pnl": 5177.61,
      "side_pnl": 7495.98
    },
    {
      "step": 750000,
      "reward": 5.8252,
      "capital": 11828.38,
      "pnl": 12589.1,
      "trades": 3976,
      "win_rate": 0.657,
      "fees": 3520.42,
      "sharpe": 27.04,
      "trend_trades": 1060,
      "side_trades": 2916,
      "trend_pnl": 5234.07,
      "side_pnl": 7355.03
    },
    {
      "step": 760000,
      "reward": 6.1975,
      "capital": 12200.71,
      "pnl": 12976.94,
      "trades": 3914,
      "win_rate": 0.662,
      "fees": 3551.94,
      "sharpe": 27.47,
      "trend_trades": 1043,
      "side_trades": 2871,
      "trend_pnl": 5394.54,
      "side_pnl": 7582.4
    },
    {
      "step": 770000,
      "reward": 6.2528,
      "capital": 12273.22,
      "pnl": 13051.85,
      "trades": 3919,
      "win_rate": 0.663,
      "fees": 3556.65,
      "sharpe": 27.55,
      "trend_trades": 1056,
      "side_trades": 2863,
      "trend_pnl": 5412.27,
      "side_pnl": 7639.58
    },
    {
      "step": 780000,
      "reward": 6.072,
      "capital": 12142.68,
      "pnl": 12915.29,
      "trades": 3900,
      "win_rate": 0.661,
      "fees": 3544.64,
      "sharpe": 27.44,
      "trend_trades": 1045,
      "side_trades": 2855,
      "trend_pnl": 5329.26,
      "side_pnl": 7586.02
    },
    {
      "step": 790000,
      "reward": 5.9702,
      "capital": 12039.24,
      "pnl": 12804.0,
      "trades": 3900,
      "win_rate": 0.662,
      "fees": 3529.26,
      "sharpe": 27.3,
      "trend_trades": 1040,
      "side_trades": 2860,
      "trend_pnl": 5284.63,
      "side_pnl": 7519.37
    },
    {
      "step": 800000,
      "reward": 6.0869,
      "capital": 12092.51,
      "pnl": 12871.13,
      "trades": 3943,
      "win_rate": 0.661,
      "fees": 3557.04,
      "sharpe": 27.42,
      "trend_trades": 1056,
      "side_trades": 2887,
      "trend_pnl": 5350.42,
      "side_pnl": 7520.71
    }
  ]
}